sperm/__init__.py
sperm/_shape_prior.py
sperm/linear_model/__init__.py
sperm/linear_model/_base.py
sperm/linear_model/_ridge.py
sperm/neural_network/__init__.py
sperm/neural_network/_multilayer_perceptron.py
sperm-0.0.1.dist-info/METADATA
sperm-0.0.1.dist-info/WHEEL
sperm-0.0.1.dist-info/licenses/LICENSE
sperm-0.0.1.dist-info/RECORD
