Metadata-Version: 2.1
Name: sperm
Version: 0.0.1
Summary: SPERM (Shape Prior Embedded Regression Models) targets providing flexible shape prior embeddings into base regression models.
Project-URL: Homepage, https://github.com/XiangCHEN-dvi/sperm
Project-URL: Bug Tracker, https://github.com/XiangCHEN-dvi/sperm/issues
Author-email: Xiang CHEN <xiangchen.ai@outlook.com>
License-File: LICENSE
Classifier: License :: OSI Approved :: Apache Software License
Classifier: Operating System :: OS Independent
Classifier: Programming Language :: Python :: 3
Requires-Python: >=3.7
